{"train/box_loss": 0.53089, "train/cls_loss": 0.49994, "train/dfl_loss": 2.04089, "_timestamp": 1715610065.6908193, "lr/pg0": 0.00023567, "lr/pg1": 0.00023567, "lr/pg2": 0.00023567, "metrics/precision(B)": 0.75442, "metrics/recall(B)": 0.53825, "metrics/mAP50(B)": 0.65401, "metrics/mAP50-95(B)": 0.50534, "val/box_loss": 0.92917, "val/cls_loss": 0.96169, "val/dfl_loss": 2.47354, "labels": {"_type": "image-file", "sha256": "3652fa9004ecb518ca8f9a7a5af57291040c27db44e0f8159f39e6a6878fb650", "size": 152187, "path": "media/images/labels_1_3652fa9004ecb518ca8f.jpg", "format": "jpg", "width": 1600, "height": 1600}, "train_batch1": {"_type": "image-file", "sha256": "00b1b74524aa790ce1242b358bb94cf143cc9ddfc0af8826a03dbcf1a0ab511f", "size": 108606, "path": "media/images/train_batch1_1_00b1b74524aa790ce124.jpg", "format": "jpg", "width": 1280, "height": 1280}, "train_batch0": {"_type": "image-file", "sha256": "377b82498bb8fb12f5024802bf02de40cb36a86e86fcdad15df3c1fd9da1574a", "size": 95439, "path": "media/images/train_batch0_1_377b82498bb8fb12f502.jpg", "format": "jpg", "width": 1280, "height": 1280}, "train_batch2": {"_type": "image-file", "sha256": "f1d3e2764267f8ccf4883df17719ee602d38e01d4d16e60cfb060fe44b3202bc", "size": 79410, "path": "media/images/train_batch2_1_f1d3e2764267f8ccf488.jpg", "format": "jpg", "width": 1280, "height": 1280}, "model/parameters": 69494019, "model/GFLOPs": 263.975, "model/speed_PyTorch(ms)": 71.795, "_runtime": 2601.5507543087006, "_step": 535}